odoo/addons/partner_event/README.rst
odoo/addons/partner_event/__init__.py
odoo/addons/partner_event/__manifest__.py
odoo/addons/partner_event/i18n/es.po
odoo/addons/partner_event/i18n/sl.po
odoo/addons/partner_event/models/__init__.py
odoo/addons/partner_event/models/event_event.py
odoo/addons/partner_event/models/event_registration.py
odoo/addons/partner_event/models/res_partner.py
odoo/addons/partner_event/static/description/icon.png
odoo/addons/partner_event/tests/__init__.py
odoo/addons/partner_event/tests/test_event_registration.py
odoo/addons/partner_event/views/event_event_view.xml
odoo/addons/partner_event/views/event_registration_view.xml
odoo/addons/partner_event/views/res_partner_view.xml
odoo/addons/partner_event/wizard/__init__.py
odoo/addons/partner_event/wizard/res_partner_register_event.py
odoo/addons/partner_event/wizard/res_partner_register_event_view.xml
odoo11_addon_partner_event-11.0.2.1.0.dist-info/METADATA
odoo11_addon_partner_event-11.0.2.1.0.dist-info/RECORD
odoo11_addon_partner_event-11.0.2.1.0.dist-info/WHEEL
odoo11_addon_partner_event-11.0.2.1.0.dist-info/top_level.txt
